<?xml version="1.0" encoding="UTF-8"?>
<tumblr version="1.0">
    <tumblelog name="apitest1" timezone="US/Eastern" title="Untitled"></tumblelog>
    <posts start="10" total="4">
        <post id="154005356017" url="https://apitest1.tumblr.com/post/154005356017" url-with-slug="https://apitest1.tumblr.com/post/154005356017/can-caption-be-styled" type="photo" date-gmt="2016-12-03 23:07:55 GMT" date="Sat, 03 Dec 2016 18:07:55" unix-timestamp="1480806475" format="html" reblog-key="mJffi91H" slug="can-caption-be-styled" width="718" height="391">
            <photo-caption>&lt;p&gt;Can caption be &lt;b&gt;styled&lt;/b&gt;?&lt;/p&gt;</photo-caption>
            <photo-url max-width="1280">https://68.media.tumblr.com/ca4ceab2736d1d88125f9e9f104ad376/tumblr_ohmtl7Aen41vma4uho1_1280.png</photo-url>
            <photo-url max-width="500">https://68.media.tumblr.com/ca4ceab2736d1d88125f9e9f104ad376/tumblr_ohmtl7Aen41vma4uho1_500.png</photo-url>
            <photo-url max-width="400">https://68.media.tumblr.com/ca4ceab2736d1d88125f9e9f104ad376/tumblr_ohmtl7Aen41vma4uho1_400.png</photo-url>
            <photo-url max-width="250">https://68.media.tumblr.com/ca4ceab2736d1d88125f9e9f104ad376/tumblr_ohmtl7Aen41vma4uho1_250.png</photo-url>
            <photo-url max-width="100">https://68.media.tumblr.com/ca4ceab2736d1d88125f9e9f104ad376/tumblr_ohmtl7Aen41vma4uho1_100.png</photo-url>
            <photo-url max-width="75">https://68.media.tumblr.com/ca4ceab2736d1d88125f9e9f104ad376/tumblr_ohmtl7Aen41vma4uho1_75sq.png</photo-url>
        </post>
        <post id="154005322782" url="https://apitest1.tumblr.com/post/154005322782" url-with-slug="https://apitest1.tumblr.com/post/154005322782/hello-markdown" type="regular" date-gmt="2016-12-03 23:06:53 GMT" date="Sat, 03 Dec 2016 18:06:53" unix-timestamp="1480806413" format="markdown" reblog-key="wDY5YAJk" slug="hello-markdown">
            <regular-body>&lt;h1&gt;Hello&lt;/h1&gt;
                
                &lt;h3&gt;Markdown&lt;/h3&gt;</regular-body>
        </post>
        <post id="154005284812" url="https://apitest1.tumblr.com/post/154005284812" url-with-slug="https://apitest1.tumblr.com/post/154005284812" type="regular" date-gmt="2016-12-03 23:05:42 GMT" date="Sat, 03 Dec 2016 18:05:42" unix-timestamp="1480806342" format="html" reblog-key="riQUYgVl" slug="">
            <regular-body>&lt;figure class="tmblr-full" data-orig-height="391" data-orig-width="718"&gt;&lt;img src="https://68.media.tumblr.com/ca4ceab2736d1d88125f9e9f104ad376/tumblr_inline_ohmth72dvU1uahjn5_540.png" data-orig-height="391" data-orig-width="718"/&gt;&lt;/figure&gt;&lt;figure class="tmblr-full" data-orig-height="391" data-orig-width="718"&gt;&lt;img src="https://68.media.tumblr.com/ca4ceab2736d1d88125f9e9f104ad376/tumblr_inline_ohmthfr5KC1uahjn5_540.png" data-orig-height="391" data-orig-width="718"/&gt;&lt;/figure&gt;</regular-body>
        </post>
        <post id="154005197267" url="https://apitest1.tumblr.com/post/154005197267" url-with-slug="https://apitest1.tumblr.com/post/154005197267/title-example" type="regular" date-gmt="2016-12-03 23:03:13 GMT" date="Sat, 03 Dec 2016 18:03:13" unix-timestamp="1480806193" format="html" reblog-key="DqD4i7ca" slug="title-example">
            <regular-title>Title Example</regular-title>
            <regular-body>&lt;p&gt;This is &lt;b&gt;body&lt;/b&gt;. Can it be &lt;strike&gt;styled&lt;/strike&gt;?&lt;/p&gt;</regular-body>
            <tag>where will it appear</tag>
        </post>
    </posts>
</tumblr>
